shooortcuts/__init__.py
shooortcuts/common.py
shooortcuts/rsimg.py
shooortcuts-1.0.1.dist-info/METADATA
shooortcuts-1.0.1.dist-info/WHEEL
shooortcuts-1.0.1.dist-info/entry_points.txt
shooortcuts-1.0.1.dist-info/top_level.txt
shooortcuts-1.0.1.dist-info/RECORD
