Metadata-Version: 2.4
Name: shooortcuts
Version: 1.0.1
Summary: Simple and helpful cli shortcuts.
Author: monosolo101
Author-email: monosolo1on1@gmail.com
Keywords: git,utility,commands
Requires-Python: >=3.6
Requires-Dist: gitpython>=3.1.0
Requires-Dist: pillow==11.3.0
Dynamic: author
Dynamic: author-email
Dynamic: description
Dynamic: description-content-type
Dynamic: keywords
Dynamic: requires-dist
Dynamic: requires-python
Dynamic: summary
